promptbind/__init__.py
promptbind/bank.py
promptbind/container.py
promptbind/decorator.py
promptbind/util.py
promptbind-0.2.2.dist-info/METADATA
promptbind-0.2.2.dist-info/WHEEL
promptbind-0.2.2.dist-info/RECORD
