Metadata-Version: 2.4
Name: promptbind
Version: 0.2.2
Summary: Add your description here
Requires-Python: >=3.10
Requires-Dist: dataclasses>=0.8
Requires-Dist: jinja2>=3.1.6
Requires-Dist: toml>=0.10.2
